{
  "subject": "master_scoreboard_mlb_2015_04_05",
  "copyright": "Copyright 2015 MLB Advanced Media, L.P.  Use of any content on this page acknowledges agreement to the terms posted here http://gdx.mlb.com/components/copyright.txt",
  "data": {
    "games": {
      "next_day_date": "2015-04-06",
      "modified_date": "2015-04-04T00:35:14Z",
      "month": "04",
      "year": "2015",
      "game": {
        "game_type": "R",
        "double_header_sw": "N",
        "location": "Chicago",
        "away_time": "7:05",
        "broadcast": {
          "away": {
            "tv": "ESPN2",
            "radio": "CRN, KMOX 1120"
          },
          "home": {
            "tv": "ESPN2",
            "radio": "WBBM 780, Cubs Radio Network"
          }
        },
        "time": "8:05",
        "home_time": "7:05",
        "home_team_name": "Cubs",
        "description": "Cubs home opener",
        "original_date": "2015/04/05",
        "home_team_city": "Chi Cubs",
        "venue_id": "17",
        "gameday_sw": "P",
        "away_win": "0",
        "home_games_back_wildcard": "",
        "away_probable_pitcher": {
          "last": "Wainwright",
          "name_display_roster": "Wainwright",
          "number": "50",
          "era": "-.--",
          "id": "425794",
          "throwinghand": "RHP",
          "s_losses": "0",
          "first_name": "Adam",
          "s_era": "-.--",
          "last_name": "Wainwright",
          "losses": "0",
          "first": "Adam",
          "s_wins": "0",
          "wins": "0"
        },
        "away_team_id": "138",
        "tz_hm_lg_gen": "ET",
        "status": {
          "ind": "S",
          "status": "Preview",
          "inning_state": "",
          "note": ""
        },
        "home_loss": "0",
        "home_games_back": "",
        "home_code": "chn",
        "away_sport_code": "mlb",
        "home_win": "0",
        "time_hm_lg": "8:05",
        "away_name_abbrev": "STL",
        "league": "NN",
        "time_zone_aw_lg": "-4",
        "away_games_back": "",
        "home_file_code": "chc",
        "game_data_directory": "/components/game/mlb/year_2015/month_04/day_05/gid_2015_04_05_slnmlb_chnmlb_1",
        "time_zone": "ET",
        "away_league_id": "104",
        "home_team_id": "112",
        "day": "SUN",
        "time_aw_lg": "8:05",
        "away_team_city": "St. Louis",
        "tbd_flag": "N",
        "tz_aw_lg_gen": "ET",
        "away_code": "sln",
        "game_media": {
          "media": {
            "free": "NO",
            "title": "STL @ CHC",
            "thumbnail": "http://mediadownloads.mlb.com/mlbam/preview/slnchn_413661_th_7_preview.jpg",
            "media_state": "media_off",
            "start": "2015-04-05T20:05:00-0400",
            "has_mlbtv": "true",
            "calendar_event_id": "14-413661-2015-04-05",
            "type": "game"
          }
        },
        "game_nbr": "1",
        "time_date_aw_lg": "2015/04/05 8:05",
        "away_games_back_wildcard": "",
        "scheduled_innings": "9",
        "venue_w_chan_loc": "USIL0225",
        "first_pitch_et": "",
        "away_team_name": "Cardinals",
        "time_date_hm_lg": "2015/04/05 8:05",
        "id": "2015/04/05/slnmlb-chnmlb-1",
        "home_name_abbrev": "CHC",
        "tiebreaker_sw": "N",
        "ampm": "PM",
        "home_division": "C",
        "home_time_zone": "CT",
        "away_time_zone": "CT",
        "hm_lg_ampm": "PM",
        "home_sport_code": "mlb",
        "time_date": "2015/04/05 8:05",
        "links": {
          "wrapup": "",
          "preview": "/mlb/gameday/index.jsp?gid=2015_04_05_slnmlb_chnmlb_1&mode=preview&c_id=mlb",
          "home_preview": "/mlb/gameday/index.jsp?gid=2015_04_05_slnmlb_chnmlb_1&mode=preview&c_id=mlb",
          "away_preview": "/mlb/gameday/index.jsp?gid=2015_04_05_slnmlb_chnmlb_1&mode=preview&c_id=mlb",
          "tv_station": "ESPN2"
        },
        "home_ampm": "PM",
        "game_pk": "413661",
        "venue": "Wrigley Field",
        "home_probable_pitcher": {
          "last": "Lester",
          "name_display_roster": "Lester",
          "number": "34",
          "era": "-.--",
          "id": "452657",
          "throwinghand": "LHP",
          "s_losses": "0",
          "first_name": "Jon",
          "s_era": "-.--",
          "last_name": "Lester",
          "losses": "0",
          "first": "Jon",
          "s_wins": "0",
          "wins": "0"
        },
        "home_league_id": "104",
        "video_thumbnail": "http://mediadownloads.mlb.com/mlbam/preview/slnchn_413661_th_7_preview.jpg",
        "away_loss": "0",
        "resume_date": "",
        "away_file_code": "stl",
        "aw_lg_ampm": "PM",
        "video_thumbnails": {
          "thumbnail": [
            {
              "content": "http://mediadownloads.mlb.com/mlbam/preview/slnchn_413661_th_7_preview.jpg",
              "height": "70",
              "scenario": "7",
              "width": "124"
            },
            {
              "content": "http://mediadownloads.mlb.com/mlbam/preview/slnchn_413661_th_37_preview.jpg",
              "height": "90",
              "scenario": "37",
              "width": "160"
            }
          ]
        },
        "time_zone_hm_lg": "-4",
        "away_ampm": "PM",
        "gameday": "2015_04_05_slnmlb_chnmlb_1",
        "away_division": "C"
      },
      "day": "05"
    }
  }
}
